cascading_upper_bounds-1.0.0.dist-info/RECORD
cascading_upper_bounds-1.0.0.dist-info/WHEEL
cascading_upper_bounds-1.0.0.dist-info/METADATA
cascading_upper_bounds-1.0.0.dist-info/licenses/LICENSE
include/Eigen/CholmodSupport
include/Eigen/StdVector
include/Eigen/StdDeque
include/Eigen/Core
include/Eigen/SparseLU
include/Eigen/OrderingMethods
include/Eigen/QtAlignedMalloc
include/Eigen/Householder
include/Eigen/PardisoSupport
include/Eigen/SparseCore
include/Eigen/Jacobi
include/Eigen/Dense
include/Eigen/SPQRSupport
include/Eigen/QR
include/Eigen/Eigen
include/Eigen/SparseQR
include/Eigen/SVD
include/Eigen/Cholesky
include/Eigen/UmfPackSupport
include/Eigen/IterativeLinearSolvers
include/Eigen/LU
include/Eigen/Sparse
include/Eigen/Geometry
include/Eigen/SuperLUSupport
include/Eigen/StdList
include/Eigen/MetisSupport
include/Eigen/SparseCholesky
include/Eigen/Eigenvalues
include/Eigen/PaStiXSupport
include/Eigen/KLUSupport
include/Eigen/src/CholmodSupport/CholmodSupport.h
include/Eigen/src/misc/blas.h
include/Eigen/src/misc/lapacke.h
include/Eigen/src/misc/Kernel.h
include/Eigen/src/misc/RealSvd2x2.h
include/Eigen/src/misc/Image.h
include/Eigen/src/misc/lapack.h
include/Eigen/src/misc/lapacke_mangling.h
include/Eigen/src/Core/Reverse.h
include/Eigen/src/Core/ConditionEstimator.h
include/Eigen/src/Core/PermutationMatrix.h
include/Eigen/src/Core/Assign.h
include/Eigen/src/Core/MathFunctionsImpl.h
include/Eigen/src/Core/CwiseUnaryOp.h
include/Eigen/src/Core/DiagonalMatrix.h
include/Eigen/src/Core/StlIterators.h
include/Eigen/src/Core/VectorBlock.h
include/Eigen/src/Core/ReturnByValue.h
include/Eigen/src/Core/Solve.h
include/Eigen/src/Core/ArithmeticSequence.h
include/Eigen/src/Core/Product.h
include/Eigen/src/Core/MatrixBase.h
include/Eigen/src/Core/Stride.h
include/Eigen/src/Core/Map.h
include/Eigen/src/Core/ForceAlignedAccess.h
include/Eigen/src/Core/MathFunctions.h
include/Eigen/src/Core/SelfCwiseBinaryOp.h
include/Eigen/src/Core/BandMatrix.h
include/Eigen/src/Core/Inverse.h
include/Eigen/src/Core/Assign_MKL.h
include/Eigen/src/Core/Swap.h
include/Eigen/src/Core/ProductEvaluators.h
