Metadata-Version: 2.1
Name: cascading-upper-bounds
Version: 1.0.0
Summary: Implementation of Cascading upper bounds for triangle soup Pompeiu-Hausdorff distance
Author-Email: Leonardo Sacht <leonardo.sacht@ufsc.br>, Alec Jacobson <alecjacobson@gmail.com>
Classifier: License :: OSI Approved :: Mozilla Public License 2.0 (MPL 2.0)
Project-URL: Homepage, https://github.com/leokollersacht/pompeiu_hausdorff
Requires-Python: >=3.8
